bulloh/__init__.py
bulloh/bulloh.py
bulloh/health_connect_client.py
bulloh/rescuetime_client.py
bulloh/s3_client.py
bulloh-0.1.19.dist-info/METADATA
bulloh-0.1.19.dist-info/WHEEL
bulloh-0.1.19.dist-info/licenses/LICENSE
bulloh-0.1.19.dist-info/RECORD
