Metadata-Version: 2.4
Name: bulloh
Version: 0.1.19
Summary: Script to automate gathering personal productivity data.
License-File: LICENSE
Author: anggelomos
Author-email: anggelomos@outlook.com
Requires-Python: >=3.10,<4.0
Classifier: Programming Language :: Python :: 3
Classifier: Programming Language :: Python :: 3.10
Classifier: Programming Language :: Python :: 3.11
Classifier: Programming Language :: Python :: 3.12
Classifier: Programming Language :: Python :: 3.13
Classifier: Programming Language :: Python :: 3.14
Requires-Dist: boto3 (>=1.40.74,<2.0.0)
Requires-Dist: cattrs
Requires-Dist: nothion (>=0.4.9,<0.5.0)
Requires-Dist: python-dotenv (>=1.1.1,<2.0.0)
Requires-Dist: tickthon (>=0.2.9)
Project-URL: repository, https://github.com/anggelomos/bulloh
